<?xml version = '1.0' encoding = 'UTF-8'?>
<TableProxyOraclev11g class="oracle.dbtools.crest.model.design.storage.oracle.v11g.TableProxyOraclev11g" name="POS_RE_2014_FECHO_MENSAL_RUBR" directorySegmentName="seg_0" id="3F35B338-ACA0-EA77-32C8-5EF61548DAAF">
<createdBy>DC_FRAMOS</createdBy>
<createdTime>2023-03-27 09:50:09 UTC</createdTime>
<ownerDesignName>MAJ_MAIN_DIAGRAM</ownerDesignName>
<schemaObject>D0C5D8A5-22DC-D4F7-93E7-57ABDA45C7E8</schemaObject>
<logging>YES</logging>
<partitionedRowMovement>DISABLE</partitionedRowMovement>
<segment>EE7E8E9B-00D3-421B-1CE1-FC586A38F3C0</segment>
<tableSpace>6A700388-81FC-E3F4-ADD6-54CA40FEC928</tableSpace>
<temporaryChanged>false</temporaryChanged>
<accessDriverType>oracle_loader</accessDriverType>
<rejectLimit></rejectLimit>
<columnProxies itemClass="oracle.dbtools.crest.model.design.storage.oracle.v12c.ColumnProxyOraclev12c">
<ColumnProxy name="ANO" id="10C89548-63F5-695F-BD9D-71C66B851A6D">
<createdBy>DC_FRAMOS</createdBy>
<createdTime>2023-03-27 09:50:19 UTC</createdTime>
<ownerDesignName>MAJ_MAIN_DIAGRAM</ownerDesignName>
</ColumnProxy>
<ColumnProxy name="MES" id="1DC59801-9122-CF3A-5B68-178D516E2D89">
<createdBy>DC_FRAMOS</createdBy>
<createdTime>2023-03-27 09:50:19 UTC</createdTime>
<ownerDesignName>MAJ_MAIN_DIAGRAM</ownerDesignName>
</ColumnProxy>
<ColumnProxy name="USER_ALTERACAO" id="1E4AC36B-FB5B-B86D-A6AD-4DAD563F9A99">
<createdBy>DC_FRAMOS</createdBy>
<createdTime>2023-03-27 09:50:19 UTC</createdTime>
<ownerDesignName>MAJ_MAIN_DIAGRAM</ownerDesignName>
</ColumnProxy>
<ColumnProxy name="STATUS_DW" id="2AF5130B-92D5-8A82-EBA8-BAC5C4C0C455">
<createdBy>DC_FRAMOS</createdBy>
<createdTime>2023-03-27 09:50:19 UTC</createdTime>
<ownerDesignName>MAJ_MAIN_DIAGRAM</ownerDesignName>
</ColumnProxy>
<ColumnProxy name="TIPO_RUBRICA" id="6D76BB0A-9A27-4483-891E-B1DD5160ED79">
<createdBy>DC_FRAMOS</createdBy>
<createdTime>2023-03-27 09:50:19 UTC</createdTime>
<ownerDesignName>MAJ_MAIN_DIAGRAM</ownerDesignName>
</ColumnProxy>
<ColumnProxy name="STATUS_EDW" id="85F274C3-0CC6-BA3B-4137-B76130717762">
<createdBy>DC_FRAMOS</createdBy>
<createdTime>2023-03-27 09:50:19 UTC</createdTime>
<ownerDesignName>MAJ_MAIN_DIAGRAM</ownerDesignName>
</ColumnProxy>
<ColumnProxy name="STATUS" id="F72D12AD-5E0B-D5A6-26D9-0A5CCB061377">
<createdBy>DC_FRAMOS</createdBy>
<createdTime>2023-03-27 09:50:19 UTC</createdTime>
<ownerDesignName>MAJ_MAIN_DIAGRAM</ownerDesignName>
</ColumnProxy>
<ColumnProxy name="DATA_ALTERACAO" id="FC84BB45-12B6-C639-5D94-333B4BB9A146">
<createdBy>DC_FRAMOS</createdBy>
<createdTime>2023-03-27 09:50:19 UTC</createdTime>
<ownerDesignName>MAJ_MAIN_DIAGRAM</ownerDesignName>
</ColumnProxy>
</columnProxies>
</TableProxyOraclev11g>
